{
    "currency":"",
    "responseGameTransactionId":"",
    "transactionId":"",
    "bonus":null,
    "balance":"",
    "errorCode":null,
    "message":"",
    "date":"",
    "token":"",
    "signature":"",
    "status":null,
    "userId":"",
    "requestUUID":"",
    "sessionId":"",
    "apiVersion":"",
    "operatorId":"",
    "roundId":"",
    "amount":"",
    "userName":"",
    "language":"",
    "supplierId":"",
    "request":"",
    "provider":"",
    "oldBalance":"$responseG->saldo + $amount"
}